aline_ai-0.7.3.dist-info/licenses/LICENSE
realign/__init__.py
realign/agent_names.py
realign/auth.py
realign/claude_detector.py
realign/cli.py
realign/codex_detector.py
realign/codex_home.py
realign/codex_terminal_linker.py
realign/config.py
realign/context.py
realign/file_lock.py
realign/hooks.py
realign/llm_client.py
realign/logging_config.py
realign/mcp_server.py
realign/mcp_watcher.py
realign/redactor.py
realign/watcher_core.py
realign/watcher_daemon.py
realign/worker_core.py
realign/worker_daemon.py
realign/adapters/__init__.py
realign/adapters/base.py
realign/adapters/claude.py
realign/adapters/codex.py
realign/adapters/gemini.py
realign/adapters/registry.py
realign/claude_hooks/__init__.py
realign/claude_hooks/permission_request_hook.py
realign/claude_hooks/permission_request_hook_installer.py
realign/claude_hooks/stop_hook.py
realign/claude_hooks/stop_hook_installer.py
realign/claude_hooks/terminal_state.py
realign/claude_hooks/user_prompt_submit_hook.py
realign/claude_hooks/user_prompt_submit_hook_installer.py
realign/commands/__init__.py
realign/commands/add.py
realign/commands/agent.py
realign/commands/auth.py
realign/commands/config.py
realign/commands/context.py
realign/commands/doctor.py
realign/commands/export_shares.py
realign/commands/import_shares.py
realign/commands/init.py
realign/commands/restore.py
realign/commands/search.py
realign/commands/sync_agent.py
realign/commands/upgrade.py
realign/commands/watcher.py
realign/commands/worker.py
realign/dashboard/__init__.py
realign/dashboard/app.py
realign/dashboard/clipboard.py
realign/dashboard/layout.py
realign/dashboard/local_api.py
realign/dashboard/state.py
realign/dashboard/terminal_backend.py
realign/dashboard/tmux_manager.py
realign/dashboard/backends/__init__.py
realign/dashboard/backends/iterm2.py
realign/dashboard/backends/kitty.py
realign/dashboard/screens/__init__.py
realign/dashboard/screens/agent_detail.py
realign/dashboard/screens/create_agent.py
realign/dashboard/screens/create_agent_info.py
aline_ai-0.7.3.dist-info/METADATA
aline_ai-0.7.3.dist-info/WHEEL
aline_ai-0.7.3.dist-info/entry_points.txt
aline_ai-0.7.3.dist-info/top_level.txt
aline_ai-0.7.3.dist-info/RECORD
