Metadata-Version: 2.4
Name: aline-ai
Version: 0.7.3
Summary: Shared AI memory; everyone knows everything in teams
Author: Sharemind
License: MIT
Project-URL: Homepage, https://github.com/human-re/aline
Project-URL: Repository, https://github.com/human-re/aline
Project-URL: Documentation, https://github.com/human-re/aline#readme
Project-URL: Bug Tracker, https://github.com/human-re/aline/issues
Keywords: ai,agent,chat,history,mcp,claude,session-tracking,context-preservation
Classifier: Development Status :: 3 - Alpha
Classifier: Intended Audience :: Developers
Classifier: Programming Language :: Python :: 3
Classifier: Programming Language :: Python :: 3.11
Classifier: Programming Language :: Python :: 3.12
Classifier: Programming Language :: Python :: 3.13
Classifier: License :: OSI Approved :: MIT License
Classifier: Operating System :: OS Independent
Requires-Python: >=3.11
License-File: LICENSE
Requires-Dist: typer>=0.9.0
Requires-Dist: pyyaml>=6.0
Requires-Dist: rich>=13.0.0
Requires-Dist: mcp>=1.0.0
Requires-Dist: anthropic>=0.18.0
Requires-Dist: openai>=1.0.0
Requires-Dist: detect-secrets>=1.4.0
Requires-Dist: git-filter-repo>=2.38.0
Requires-Dist: cryptography>=41.0.0
Requires-Dist: httpx>=0.24.0
Requires-Dist: scikit-learn>=1.3.0
Requires-Dist: numpy>=1.24.0
Requires-Dist: textual>=0.50.0
Provides-Extra: dev
Requires-Dist: pytest>=7.0.0; extra == "dev"
Requires-Dist: pytest-cov>=4.0.0; extra == "dev"
Requires-Dist: black>=23.0.0; extra == "dev"
Requires-Dist: mypy>=1.0.0; extra == "dev"
Requires-Dist: bump-my-version>=0.26.0; extra == "dev"
Dynamic: license-file
